MANIFEST.in
README.md
setup.py
Dali/__init__.py
Dali/start.py
DaliAI.egg-info/PKG-INFO
DaliAI.egg-info/SOURCES.txt
DaliAI.egg-info/dependency_links.txt
DaliAI.egg-info/not-zip-safe
DaliAI.egg-info/top_level.txt