Metadata-Version: 2.1
Name: DaliAI
Version: 0.0.2
Summary: used for AI to change the world!
Home-page: UNKNOWN
Author: fuhao
Author-email: 54173723@qq.com
License: UNKNOWN
Platform: UNKNOWN
Classifier: Programming Language :: Python :: 3
Classifier: License :: OSI Approved :: MIT License
Classifier: Operating System :: OS Independent
